<?xml version="1.0" encoding="utf-8" ?>
<c2eventsheet>
    <!--All the 'name' attributes are ignored by Construct 2 - they are there for readability only.-->
    <name>fondo</name>
    <events>
        <event-block sid="8072812518062244">
            <conditions>
                <condition id="4" name="On finished" sid="6682706819259262" type="EsHist1v2">
                    <param id="0" name="Animation">&quot;f1&quot;</param>
                </condition>
            </conditions>
            <actions>
                <action id="-15" name="Set visible" sid="9933754805136705" type="botonNext">
                    <param id="0" name="Visibility">1</param>
                </action>
                <action id="-15" name="Set visible" sid="2964262626406252" type="botonPrev">
                    <param id="0" name="Visibility">1</param>
                </action>
            </actions>
        </event-block>
    </events>
</c2eventsheet>
